testing.cassandra-1.2.0-py2.7-nspkg.pth
testing/cassandra.py
testing.cassandra-1.2.0.dist-info/DESCRIPTION.rst
testing.cassandra-1.2.0.dist-info/METADATA
testing.cassandra-1.2.0.dist-info/RECORD
testing.cassandra-1.2.0.dist-info/WHEEL
testing.cassandra-1.2.0.dist-info/metadata.json
testing.cassandra-1.2.0.dist-info/namespace_packages.txt
testing.cassandra-1.2.0.dist-info/top_level.txt
