Metadata-Version: 2.0
Name: testing.cassandra
Version: 1.2.0
Summary: automatically setups a cassandra instance in a temporary directory, and destroys it after testing
Home-page: https://github.com/tk0miya/testing.cassandra
Author: Takeshi Komiya
Author-email: i.tkomiya at gmail.com
License: Apache License 2.0
Platform: UNKNOWN
Classifier: Development Status :: 4 - Beta
Classifier: Intended Audience :: Developers
Classifier: License :: OSI Approved :: Apache Software License
Classifier: Programming Language :: Python
Classifier: Programming Language :: Python :: 2.6
Classifier: Programming Language :: Python :: 2.7
Classifier: Topic :: Database
Classifier: Topic :: Software Development
Classifier: Topic :: Software Development :: Testing
Requires-Dist: PyYAML
Requires-Dist: pycassa
Requires-Dist: testing.common.database
Provides-Extra: testing
Requires-Dist: mock; extra == 'testing'
Requires-Dist: nose; extra == 'testing'
